{
  "month": "2012-12",
  "total_articles": 75,
  "deep_topics_summary": [
    {
      "topic_id": 0,
      "topic_name": "Corporate Tax Rates and Fiscal Policy",
      "core_keywords": ["tax", "rate", "corporate", "ceo", "bush", "compensation", "billion"],
      "importance_ratio": 0.0133
    },
    {
      "topic_id": 1,
      "topic_name": "Gun Policy and Republican Post-election Politics",
      "core_keywords": ["gun", "republican", "state", "law", "president", "party", "labor"],
      "importance_ratio": 0.5733
    },
    {
      "topic_id": 2,
      "topic_name": "Poverty and Low-wage Worker Issues",
      "core_keywords": ["poverty", "wage", "worker", "child", "housing", "homelessness", "family"],
      "importance_ratio": 0.0400
    },
    {
      "topic_id": 3,
      "topic_name": "Income Tax and Economic Policy Debates",
      "core_keywords": ["tax", "income", "republican", "rate", "cut", "social", "benefit"],
      "importance_ratio": 0.2400
    },
    {
      "topic_id": 4,
      "topic_name": "Election Polling and Drug Policy",
      "core_keywords": ["election", "obama", "vote", "poll", "drug", "state", "money"],
      "importance_ratio": 0.1333
    }
  ]
}